myloguru/__init__.py
myloguru/_resources.py
myloguru/mailer.py
myloguru/my_loguru.py
myloguru_deskent-0.1.1.data/scripts/my_loguru.py
myloguru_deskent-0.1.1.dist-info/LICENSE
myloguru_deskent-0.1.1.dist-info/METADATA
myloguru_deskent-0.1.1.dist-info/WHEEL
myloguru_deskent-0.1.1.dist-info/top_level.txt
myloguru_deskent-0.1.1.dist-info/RECORD
