Metadata-Version: 2.1
Name: myloguru-deskent
Version: 0.1.1
Summary: My loguru config
Home-page: https://github.com/Deskent/my_loguru
Author: Deskent
Author-email: battenetciz@gmail.com
Classifier: Programming Language :: Python :: 3
Classifier: License :: OSI Approved :: MIT License
Classifier: Operating System :: OS Independent
Requires-Python: >=3.8
License-File: LICENSE
Requires-Dist: loguru (==0.5.3)
